.gitignore
LICENSE
README.md
pyproject.toml
envkeeper/__init__.py
envkeeper/container.py
envkeeper-0.0.3.dist-info/METADATA
envkeeper-0.0.3.dist-info/WHEEL
envkeeper-0.0.3.dist-info/licenses/LICENSE
envkeeper-0.0.3.dist-info/RECORD
