Metadata-Version: 2.1
Name: envkeeper
Version: 0.0.3
Summary: Use environmental variables to store global data. Like localStorage, but for python!
Project-URL: GitHub, https://github.com/christopherwoodall/blobstorage
Author-email: Christopher Woodall <woodall.christopher@gmail.com>
License-Expression: MIT
License-File: LICENSE
Classifier: Development Status :: 1 - Planning
Classifier: Environment :: Console
Classifier: Framework :: Hatch
Classifier: Intended Audience :: Developers
Classifier: Intended Audience :: End Users/Desktop
Classifier: Intended Audience :: Science/Research
Classifier: License :: OSI Approved :: MIT License
Classifier: Operating System :: OS Independent
Classifier: Programming Language :: Python
Classifier: Programming Language :: Python :: 3.9
Classifier: Programming Language :: Python :: 3.10
Requires-Python: >=3.9
Requires-Dist: pre-commit
Requires-Dist: pytest
Provides-Extra: developer
Requires-Dist: hatch; extra == 'developer'
Requires-Dist: mypy; extra == 'developer'
Requires-Dist: pydantic; extra == 'developer'
Requires-Dist: types-pyyaml; extra == 'developer'
